Workbook

Sheet gap_inventory
A1: ISO 27001:2022 Annex A — 93 Control Gap Inventory
A2: Ctrl | B2: Title | C2: Theme | D2: DriftPOS-block? | E2: Current state | F2: Severity | G2: Hours | H2: Cost ($) | I2: Weeks | J2: Notes/owner
A3: 5.1 | B3: Policies for information security | C3: Org | E3: absent | F3: gap | G3: 40 | H3: =G3*assumptions!$B$3 -> 8000 | I3: =G3/(assumptions!$B$4*assumptions!$B$5) -> 0.44444444 | J3: No formal info-sec policy. Need to write one.
A4: 5.2 | B4: Information security roles and responsibilities | C4: Org | E4: weak | F4: gap | G4: 16 | H4: =G4*assumptions!$B$3 -> 3200 | I4: =G4/(assumptions!$B$4*assumptions!$B$5) -> 0.17777778 | J4: Roles informally held; not documented.
A5: 5.3 | B5: Segregation of duties | C5: Org | E5: weak | F5: partial | G5: 16 | H5: =G5*assumptions!$B$3 -> 3200 | I5: =G5/(assumptions!$B$4*assumptions!$B$5) -> 0.17777778 | J5: Senior engineers do everything; needs separation of admin from audit.
A6: 5.4 | B6: Management responsibilities | C6: Org | E6: weak | F6: partial | G6: 24 | H6: =G6*assumptions!$B$3 -> 4800 | I6: =G6/(assumptions!$B$4*assumptions!$B$5) -> 0.26666667 | J6: Owner is leader; need formal management commitment.
A7: 5.5 | B7: Contact with authorities | C7: Org | E7: weak | F7: partial | G7: 8 | H7: =G7*assumptions!$B$3 -> 1600 | I7: =G7/(assumptions!$B$4*assumptions!$B$5) -> 0.088888889 | J7: Knows local LE; needs documented contact list.
A8: 5.6 | B8: Contact with special interest groups | C8: Org | E8: absent | F8: gap | G8: 8 | H8: =G8*assumptions!$B$3 -> 1600 | I8: =G8/(assumptions!$B$4*assumptions!$B$5) -> 0.088888889 | J8: Not part of any infosec community.
A9: 5.7 | B9: Threat intelligence | C9: Org | E9: absent | F9: gap | G9: 16 | H9: =G9*assumptions!$B$3 -> 3200 | I9: =G9/(assumptions!$B$4*assumptions!$B$5) -> 0.17777778 | J9: No threat-intel program.
A10: 5.8 | B10: Information security in project management | C10: Org | E10: weak | F10: partial | G10: 8 | H10: =G10*assumptions!$B$3 -> 1600 | I10: =G10/(assumptions!$B$4*assumptions!$B$5) -> 0.088888889 | J10: Project mgmt informal; security not embedded.
A11: 5.9 | B11: Inventory of information and other associated assets | C11: Org | E11: weak | F11: gap | G11: 40 | H11: =G11*assumptions!$B$3 -> 8000 | I11: =G11/(assumptions!$B$4*assumptions!$B$5) -> 0.44444444 | J11: No formal asset inventory; deploy GCP CAI.
A12: 5.10 | B12: Acceptable use of information and other associated assets | C12: Org | E12: absent | F12: gap | G12: 8 | H12: =G12*assumptions!$B$3 -> 1600 | I12: =G12/(assumptions!$B$4*assumptions!$B$5) -> 0.088888889 | J12: Need AUP for staff and customers.
A13: 5.11 | B13: Return of assets | C13: Org | E13: moderate | F13: partial | G13: 8 | H13: =G13*assumptions!$B$3 -> 1600 | I13: =G13/(assumptions!$B$4*assumptions!$B$5) -> 0.088888889 | J13: Returns hardware on off-boarding; not documented.
A14: 5.12 | B14: Classification of information | C14: Org | E14: absent | F14: gap | G14: 16 | H14: =G14*assumptions!$B$3 -> 3200 | I14: =G14/(assumptions!$B$4*assumptions!$B$5) -> 0.17777778 | J14: No data classification scheme.
... A16: 5.14 | B16: Information transfer | C16: Org | E16: weak | F16: partial | G16: 16 | H16: =G16*assumptions!$B$3 -> 3200 | I16: =G16/(assumptions!$B$4*assumptions!$B$5) -> 0.17777778 | J16: Transfers happen via email; need governance.
A17: 5.15 | B17: Access control | C17: Org | D17: YES | E17: moderate | F17: partial | G17: 32 | H17: =G17*assumptions!$B$3 -> 6400 | I17: =G17/(assumptions!$B$4*assumptions!$B$5) -> 0.35555556 | J17: Counterpoint has access control; modernization needs IAM.
A18: 5.16 | B18: Identity management | C18: Org | E18: weak | F18: partial | G18: 24 | H18: =G18*assumptions!$B$3 -> 4800 | I18: =G18/(assumptions!$B$4*assumptions!$B$5) -> 0.26666667 | J18: Identity is per-system; need lifecycle process.
A19: 5.17 | B19: Authentication information | C19: Org | D19: YES | E19: moderate | F19: partial | G19: 24 | H19: =G19*assumptions!$B$3 -> 4800 | I19: =G19/(assumptions!$B$4*assumptions!$B$5) -> 0.26666667 | J19: Passwords/keys handled informally.
A20: 5.18 | B20: Access rights | C20: Org | E20: weak | F20: partial | G20: 16 | H20: =G20*assumptions!$B$3 -> 3200 | I20: =G20/(assumptions!$B$4*assumptions!$B$5) -> 0.17777778 | J20: Provisioning ad-hoc; de-provisioning has gaps.
A21: 5.19 | B21: Information security in supplier relationships | C21: Org | E21: absent | F21: gap | G21: 16 | H21: =G21*assumptions!$B$3 -> 3200 | I21: =G21/(assumptions!$B$4*assumptions!$B$5) -> 0.17777778 | J21: No vendor risk mgmt.
A22: 5.20 | B22: Addressing info-sec within supplier agreements | C22: Org | E22: weak | F22: partial | G22: 16 | H22: =G22*assumptions!$B$3 -> 3200 | I22: =G22/(assumptions!$B$4*assumptions!$B$5) -> 0.17777778 | J22: Some vendor contracts have security clauses; not all.
A23: 5.21 | B23: Managing info-sec in the ICT supply chain | C23: Org | E23: absent | F23: gap | G23: 16 | H23: =G23*assumptions!$B$3 -> 3200 | I23: =G23/(assumptions!$B$4*assumptions!$B$5) -> 0.17777778 | J23: Supply chain risk not analyzed.
A24: 5.22 | B24: Monitoring/review/change mgmt of supplier services | C24: Org | E24: absent | F24: gap | G24: 16 | H24: =G24*assumptions!$B$3 -> 3200 | I24: =G24/(assumptions!$B$4*assumptions!$B$5) -> 0.17777778 | J24: No vendor monitoring program.
A25: 5.23 | B25: Information security for use of cloud services | C25: Org | D25: YES | E25: absent | F25: gap | G25: 32 | H25: =G25*assumptions!$B$3 -> 6400 | I25: =G25/(assumptions!$B$4*assumptions!$B$5) -> 0.35555556 | J25: Cloud governance from scratch — Org policies needed.
A26: 5.24 | B26: IS incident management planning and preparation | C26: Org | D26: YES | E26: weak | F26: partial | G26: 24 | H26: =G26*assumptions!$B$3 -> 4800 | I26: =G26/(assumptions!$B$4*assumptions!$B$5) -> 0.26666667 | J26: Informal IR; need plan + tabletop.
A27: 5.25 | B27: Assessment and decision on info-sec events | C27: Org | E27: absent | F27: gap | G27: 16 | H27: =G27*assumptions!$B$3 -> 3200 | I27: =G27/(assumptions!$B$4*assumptions!$B$5) -> 0.17777778 | J27: No event triage process.
A28: 5.26 | B28: Response to info-sec incidents | C28: Org | E28: weak | F28: partial | G28: 16 | H28: =G28*assumptions!$B$3 -> 3200 | I28: =G28/(assumptions!$B$4*assumptions!$B$5) -> 0.17777778 | J28: Responds to incidents reactively; need process.
A29: 5.27 | B29: Learning from info-sec incidents | C29: Org | E29: weak | F29: partial | G29: 8 | H29: =G29*assumptions!$B$3 -> 1600 | I29: =G29/(assumptions!$B$4*assumptions!$B$5) -> 0.088888889 | J29: Postmortems happen verbally; not documented.
A30: 5.28 | B30: Collection of evidence | C30: Org | E30: weak | F30: gap | G30: 16 | H30: =G30*assumptions!$B$3 -> 3200 | I30: =G30/(assumptions!$B$4*assumptions!$B$5) -> 0.17777778 | J30: No forensic-readiness.
A31: 5.29 | B31: Information security during disruption | C31: Org | E31: weak | F31: partial | G31: 16 | H31: =G31*assumptions!$B$3 -> 3200 | I31: =G31/(assumptions!$B$4*assumptions!$B$5) -> 0.17777778 | J31: BCP exists for ops continuity, lacks infosec dimension.
A32: 5.30 | B32: ICT readiness for business continuity | C32: Org | E32: moderate | F32: partial | G32: 24 | H32: =G32*assumptions!$B$3 -> 4800 | I32: =G32/(assumptions!$B$4*assumptions!$B$5) -> 0.26666667 | J32: Backups exist; DR drills informal.
A33: 5.31 | B33: Legal/statutory/regulatory/contractual requirements | C33: Org | E33: moderate | F33: partial | G33: 16 | H33: =G33*assumptions!$B$3 -> 3200 | I33: =G33/(assumptions!$B$4*assumptions!$B$5) -> 0.17777778 | J33: Tax/PCI compliance tracked; broader regs less so.
A34: 5.32 | B34: Intellectual property rights | C34: Org | E34: moderate | F34: partial | G34: 8 | H34: =G34*assumptions!$B$3 -> 1600 | I34: =G34/(assumptions!$B$4*assumptions!$B$5) -> 0.088888889 | J34: IP policies for own work; not for customer customizations.
A35: 5.33 | B35: Protection of records | C35: Org | E35: moderate | F35: partial | G35: 16 | H35: =G35*assumptions!$B$3 -> 3200 | I35: =G35/(assumptions!$B$4*assumptions!$B$5) -> 0.17777778 | J35: Records kept; retention policy informal.
A36: 5.34 | B36: Privacy and protection of PII | C36: Org | D36: YES | E36: weak | F36: partial | G36: 32 | H36: =G36*assumptions!$B$3 -> 6400 | I36: =G36/(assumptions!$B$4*assumptions!$B$5) -> 0.35555556 | J36: PII handled per-customer convention; need centralized policy.
A37: 5.35 | B37: Independent review of info-sec | C37: Org | E37: absent | F37: gap | G37: 0 | H37: =G37*assumptions!$B$3 -> 0 | I37: =G37/(assumptions!$B$4*assumptions!$B$5) -> 0 | J37: Will become external audit by Growdirect (this!) — $0 internal cost.
A38: 5.36 | B38: Compliance with policies/rules/standards | C38: Org | E38: absent | F38: gap | G38: 16 | H38: =G38*assumptions!$B$3 -> 3200 | I38: =G38/(assumptions!$B$4*assumptions!$B$5) -> 0.17777778 | J38: No compliance monitoring.
A39: 5.37 | B39: Documented operating procedures | C39: Org | E39: weak | F39: partial | G39: 32 | H39: =G39*assumptions!$B$3 -> 6400 | I39: =G39/(assumptions!$B$4*assumptions!$B$5) -> 0.35555556 | J39: Some procedures documented; SOPs incomplete.
A40: 6.1 | B40: Screening | C40: People | E40: moderate | F40: partial | G40: 8 | H40: =G40*assumptions!$B$3 -> 1600 | I40: =G40/(assumptions!$B$4*assumptions!$B$5) -> 0.088888889 | J40: Background checks done; not formalized.
A41: 6.2 | B41: Terms and conditions of employment | C41: People | E41: moderate | F41: partial | G41: 8 | H41: =G41*assumptions!$B$3 -> 1600 | I41: =G41/(assumptions!$B$4*assumptions!$B$5) -> 0.088888889 | J41: Employment contracts include some security obligations.
A42: 6.3 | B42: Info-sec awareness, education and training | C42: People | E42: weak | F42: gap | G42: 24 | H42: =G42*assumptions!$B$3 -> 4800 | I42: =G42/(assumptions!$B$4*assumptions!$B$5) -> 0.26666667 | J42: No formal awareness training; deploy LMS.
A43: 6.4 | B43: Disciplinary process | C43: People | E43: weak | F43: partial | G43: 8 | H43: =G43*assumptions!$B$3 -> 1600 | I43: =G43/(assumptions!$B$4*assumptions!$B$5) -> 0.088888889 | J43: Disciplinary process exists; not security-specific.
A44: 6.5 | B44: Responsibilities after termination/change of employment | C44: People | D44: YES | E44: weak | F44: gap | G44: 16 | H44: =G44*assumptions!$B$3 -> 3200 | I44: =G44/(assumptions!$B$4*assumptions!$B$5) -> 0.17777778 | J44: Off-boarding inconsistent; need security checklist.
A45: 6.6 | B45: Confidentiality or non-disclosure agreements | C45: People | E45: moderate | F45: compliant | G45: 0 | H45: =G45*assumptions!$B$3 -> 0 | I45: =G45/(assumptions!$B$4*assumptions!$B$5) -> 0 | J45: NDAs in place — typical for a 20-year VAR.
A46: 6.7 | B46: Remote working | C46: People | E46: weak | F46: partial | G46: 16 | H46: =G46*assumptions!$B$3 -> 3200 | I46: =G46/(assumptions!$B$4*assumptions!$B$5) -> 0.17777778 | J46: Remote work informal; need policy + IAP.
A47: 6.8 | B47: Information security event reporting | C47: People | E47: weak | F47: partial | G47: 8 | H47: =G47*assumptions!$B$3 -> 1600 | I47: =G47/(assumptions!$B$4*assumptions!$B$5) -> 0.088888889 | J47: Reporting channel exists; not formalized.
A48: 7.1 | B48: Physical security perimeters | C48: Physical | E48: moderate | F48: partial | G48: 8 | H48: =G48*assumptions!$B$3 -> 1600 | I48: =G48/(assumptions!$B$4*assumptions!$B$5) -> 0.088888889 | J48: Office locked; basic perimeter.
A49: 7.2 | B49: Physical entry | C49: Physical | E49: moderate | F49: partial | G49: 8 | H49: =G49*assumptions!$B$3 -> 1600 | I49: =G49/(assumptions!$B$4*assumptions!$B$5) -> 0.088888889 | J49: Badge/key access; works.
A50: 7.3 | B50: Securing offices, rooms and facilities | C50: Physical | E50: moderate | F50: partial | G50: 8 | H50: =G50*assumptions!$B$3 -> 1600 | I50: =G50/(assumptions!$B$4*assumptions!$B$5) -> 0.088888889 | J50: Server room locked.
A51: 7.4 | B51: Physical security monitoring | C51: Physical | E51: weak | F51: partial | G51: 8 | H51: =G51*assumptions!$B$3 -> 1600 | I51: =G51/(assumptions!$B$4*assumptions!$B$5) -> 0.088888889 | J51: Cameras at office; not 24/7 monitored.
A52: 7.5 | B52: Protecting against physical/environmental threats | C52: Physical | E52: moderate | F52: partial | G52: 8 | H52: =G52*assumptions!$B$3 -> 1600 | I52: =G52/(assumptions!$B$4*assumptions!$B$5) -> 0.088888889 | J52: Standard fire/HVAC; no formal threat model.
A53: 7.6 | B53: Working in secure areas | C53: Physical | E53: moderate | F53: partial | G53: 4 | H53: =G53*assumptions!$B$3 -> 800 | I53: =G53/(assumptions!$B$4*assumptions!$B$5) -> 0.044444444 | J53: Server room procedures exist informally.
A54: 7.7 | B54: Clear desk and clear screen | C54: Physical | E54: weak | F54: partial | G54: 4 | H54: =G54*assumptions!$B$3 -> 800 | I54: =G54/(assumptions!$B$4*assumptions!$B$5) -> 0.044444444 | J54: Clear desk policy informal.
A55: 7.8 | B55: Equipment siting and protection | C55: Physical | E55: moderate | F55: partial | G55: 4 | H55: =G55*assumptions!$B$3 -> 800 | I55: =G55/(assumptions!$B$4*assumptions!$B$5) -> 0.044444444 | J55: Equipment sited reasonably.
A56: 7.9 | B56: Security of assets off-premises | C56: Physical | E56: weak | F56: partial | G56: 8 | H56: =G56*assumptions!$B$3 -> 1600 | I56: =G56/(assumptions!$B$4*assumptions!$B$5) -> 0.088888889 | J56: Off-premises asset controls weak.
... A62: 8.1 | B62: User end point devices | C62: Tech | E62: weak | F62: gap | G62: 40 | H62: =G62*assumptions!$B$3 -> 8000 | I62: =G62/(assumptions!$B$4*assumptions!$B$5) -> 0.44444444 | J62: No EDR/MDM. Deploy CrowdStrike + Workspace MDM.
A63: 8.2 | B63: Privileged access rights | C63: Tech | D63: YES | E63: weak | F63: gap | G63: 32 | H63: =G63*assumptions!$B$3 -> 6400 | I63: =G63/(assumptions!$B$4*assumptions!$B$5) -> 0.35555556 | J63: Privileged access ad-hoc; deploy Cloud IAM + PAM.
A64: 8.3 | B64: Information access restriction | C64: Tech | E64: weak | F64: gap | G64: 24 | H64: =G64*assumptions!$B$3 -> 4800 | I64: =G64/(assumptions!$B$4*assumptions!$B$5) -> 0.26666667 | J64: Access enforcement weak; tighten with VPC-SC + IAM.
A65: 8.4 | B65: Access to source code | C65: Tech | E65: moderate | F65: partial | G65: 16 | H65: =G65*assumptions!$B$3 -> 3200 | I65: =G65/(assumptions!$B$4*assumptions!$B$5) -> 0.17777778 | J65: Source code in private GitHub; access controls informal.
A66: 8.5 | B66: Secure authentication | C66: Tech | D66: YES | E66: weak | F66: gap | G66: 32 | H66: =G66*assumptions!$B$3 -> 6400 | I66: =G66/(assumptions!$B$4*assumptions!$B$5) -> 0.35555556 | J66: No MFA enforcement. Deploy Cloud Identity 2SV org-wide.
A67: 8.6 | B67: Capacity management | C67: Tech | E67: moderate | F67: partial | G67: 16 | H67: =G67*assumptions!$B$3 -> 3200 | I67: =G67/(assumptions!$B$4*assumptions!$B$5) -> 0.17777778 | J67: Capacity reactive; deploy Cloud Monitoring.
A68: 8.7 | B68: Protection against malware | C68: Tech | E68: weak | F68: partial | G68: 16 | H68: =G68*assumptions!$B$3 -> 3200 | I68: =G68/(assumptions!$B$4*assumptions!$B$5) -> 0.17777778 | J68: Workstation AV present; no centralized management.
A69: 8.8 | B69: Management of technical vulnerabilities | C69: Tech | E69: weak | F69: gap | G69: 32 | H69: =G69*assumptions!$B$3 -> 6400 | I69: =G69/(assumptions!$B$4*assumptions!$B$5) -> 0.35555556 | J69: No vuln scanning. Deploy Container Analysis + Wiz.
A70: 8.9 | B70: Configuration management | C70: Tech | D70: YES | E70: absent | F70: gap | G70: 64 | H70: =G70*assumptions!$B$3 -> 12800 | I70: =G70/(assumptions!$B$4*assumptions!$B$5) -> 0.71111111 | J70: No IaC. Stand up Terraform + Config Connector.
A71: 8.10 | B71: Information deletion | C71: Tech | E71: weak | F71: partial | G71: 16 | H71: =G71*assumptions!$B$3 -> 3200 | I71: =G71/(assumptions!$B$4*assumptions!$B$5) -> 0.17777778 | J71: Deletion processes ad-hoc.
A72: 8.11 | B72: Data masking | C72: Tech | E72: absent | F72: gap | G72: 24 | H72: =G72*assumptions!$B$3 -> 4800 | I72: =G72/(assumptions!$B$4*assumptions!$B$5) -> 0.26666667 | J72: No data masking. Deploy DLP API for non-prod.
A73: 8.12 | B73: Data leakage prevention | C73: Tech | E73: absent | F73: gap | G73: 32 | H73: =G73*assumptions!$B$3 -> 6400 | I73: =G73/(assumptions!$B$4*assumptions!$B$5) -> 0.35555556 | J73: No DLP. Deploy DLP API + Workspace controls.
A74: 8.13 | B74: Information backup | C74: Tech | D74: YES | E74: moderate | F74: partial | G74: 24 | H74: =G74*assumptions!$B$3 -> 4800 | I74: =G74/(assumptions!$B$4*assumptions!$B$5) -> 0.26666667 | J74: Backups exist; no recovery test. Add cross-region + drill.
A75: 8.14 | B75: Redundancy of information processing facilities | C75: Tech | E75: weak | F75: partial | G75: 24 | H75: =G75*assumptions!$B$3 -> 4800 | I75: =G75/(assumptions!$B$4*assumptions!$B$5) -> 0.26666667 | J75: Single-zone DBs; need HA + DR setup.
A76: 8.15 | B76: Logging | C76: Tech | D76: YES | E76: weak | F76: gap | G76: 32 | H76: =G76*assumptions!$B$3 -> 6400 | I76: =G76/(assumptions!$B$4*assumptions!$B$5) -> 0.35555556 | J76: Logs scattered. Centralize on Cloud Logging + sinks.
A77: 8.16 | B77: Monitoring activities | C77: Tech | D77: YES | E77: absent | F77: gap | G77: 40 | H77: =G77*assumptions!$B$3 -> 8000 | I77: =G77/(assumptions!$B$4*assumptions!$B$5) -> 0.44444444 | J77: No SIEM. Deploy SCC Premium + Chronicle.
A78: 8.17 | B78: Clock synchronization | C78: Tech | E78: moderate | F78: compliant | G78: 0 | H78: =G78*assumptions!$B$3 -> 0 | I78: =G78/(assumptions!$B$4*assumptions!$B$5) -> 0 | J78: Use GCP-managed NTP; no work needed.
A79: 8.18 | B79: Use of privileged utility programs | C79: Tech | E79: weak | F79: partial | G79: 16 | H79: =G79*assumptions!$B$3 -> 3200 | I79: =G79/(assumptions!$B$4*assumptions!$B$5) -> 0.17777778 | J79: Admin tooling informal; deploy IAP + session recording.
A80: 8.19 | B80: Installation of software on operational systems | C80: Tech | E80: weak | F80: partial | G80: 24 | H80: =G80*assumptions!$B$3 -> 4800 | I80: =G80/(assumptions!$B$4*assumptions!$B$5) -> 0.26666667 | J80: Software install controls informal.
A81: 8.20 | B81: Networks security | C81: Tech | D81: YES | E81: weak | F81: gap | G81: 40 | H81: =G81*assumptions!$B$3 -> 8000 | I81: =G81/(assumptions!$B$4*assumptions!$B$5) -> 0.44444444 | J81: Network security from scratch in cloud. VPC + Cloud Armor.
A82: 8.21 | B82: Security of network services | C82: Tech | E82: weak | F82: partial | G82: 16 | H82: =G82*assumptions!$B$3 -> 3200 | I82: =G82/(assumptions!$B$4*assumptions!$B$5) -> 0.17777778 | J82: Network services controls weak.
A83: 8.22 | B83: Segregation of networks | C83: Tech | E83: weak | F83: gap | G83: 24 | H83: =G83*assumptions!$B$3 -> 4800 | I83: =G83/(assumptions!$B$4*assumptions!$B$5) -> 0.26666667 | J83: No segmentation. Plan VPC + tenant isolation.
A84: 8.23 | B84: Web filtering | C84: Tech | E84: weak | F84: partial | G84: 16 | H84: =G84*assumptions!$B$3 -> 3200 | I84: =G84/(assumptions!$B$4*assumptions!$B$5) -> 0.17777778 | J84: Web filtering minimal; deploy Cloud DNS Forwarder.
A85: 8.24 | B85: Use of cryptography | C85: Tech | D85: YES | E85: weak | F85: gap | G85: 40 | H85: =G85*assumptions!$B$3 -> 8000 | I85: =G85/(assumptions!$B$4*assumptions!$B$5) -> 0.44444444 | J85: Encryption inconsistent. Deploy Cloud KMS comprehensively.
A86: 8.25 | B86: Secure development life cycle | C86: Tech | D86: YES | E86: absent | F86: gap | G86: 56 | H86: =G86*assumptions!$B$3 -> 11200 | I86: =G86/(assumptions!$B$4*assumptions!$B$5) -> 0.62222222 | J86: No formal SDLC. Deploy Cloud Build + Binary Auth.
A87: 8.26 | B87: Application security requirements | C87: Tech | E87: weak | F87: partial | G87: 16 | H87: =G87*assumptions!$B$3 -> 3200 | I87: =G87/(assumptions!$B$4*assumptions!$B$5) -> 0.17777778 | J87: App security requirements informal.
A88: 8.27 | B88: Secure system architecture/engineering principles | C88: Tech | E88: weak | F88: partial | G88: 24 | H88: =G88*assumptions!$B$3 -> 4800 | I88: =G88/(assumptions!$B$4*assumptions!$B$5) -> 0.26666667 | J88: Architecture review informal.
A89: 8.28 | B89: Secure coding | C89: Tech | E89: weak | F89: partial | G89: 16 | H89: =G89*assumptions!$B$3 -> 3200 | I89: =G89/(assumptions!$B$4*assumptions!$B$5) -> 0.17777778 | J89: Coding standards exist; not security-focused.
A90: 8.29 | B90: Security testing in development and acceptance | C90: Tech | E90: absent | F90: gap | G90: 40 | H90: =G90*assumptions!$B$3 -> 8000 | I90: =G90/(assumptions!$B$4*assumptions!$B$5) -> 0.44444444 | J90: No SAST/DAST. Deploy Web Security Scanner + Snyk.
A91: 8.30 | B91: Outsourced development | C91: Tech | E91: moderate | F91: compliant | G91: 0 | H91: =G91*assumptions!$B$3 -> 0 | I91: =G91/(assumptions!$B$4*assumptions!$B$5) -> 0 | J91: No outsourced dev typical for this scale.
A92: 8.31 | B92: Separation of dev/test/prod environments | C92: Tech | E92: weak | F92: partial | G92: 24 | H92: =G92*assumptions!$B$3 -> 4800 | I92: =G92/(assumptions!$B$4*assumptions!$B$5) -> 0.26666667 | J92: Env separation informal. Formalize with Org/Folder structure.
A93: 8.32 | B93: Change management | C93: Tech | E93: weak | F93: partial | G93: 16 | H93: =G93*assumptions!$B$3 -> 3200 | I93: =G93/(assumptions!$B$4*assumptions!$B$5) -> 0.17777778 | J93: Change mgmt informal; deploy Cloud Build + IaC review.
A94: 8.33 | B94: Test information | C94: Tech | E94: weak | F94: partial | G94: 16 | H94: =G94*assumptions!$B$3 -> 3200 | I94: =G94/(assumptions!$B$4*assumptions!$B$5) -> 0.17777778 | J94: Test data handling informal.
A95: 8.34 | B95: Protection of info systems during audit testing | C95: Tech | E95: moderate | F95: compliant | G95: 0 | H95: =G95*assumptions!$B$3 -> 0 | I95: =G95/(assumptions!$B$4*assumptions!$B$5) -> 0 | J95: Standard practice; no special audit-time work needed.
A96: TOTAL | G96: =SUM(G3:G95) -> 1684 | H96: =SUM(H3:H95) -> 336800 | I96: =G96/(assumptions!$B$4*assumptions!$B$5) -> 18.711111
A98: DriftPOS-blocking subset | G98: =SUMIF(D3:D95,"YES",G3:G95) -> 520 | H98: =SUMIF(D3:D95,"YES",H3:H95) -> 104000 | I98: =G98/(assumptions!$B$4*assumptions!$B$5*0.6) -> 9.6296296
A100: By theme:
A101: Org | G101: =SUMIF(C3:C95,"Org",G3:G95) -> 664 | H101: =SUMIF(C3:C95,"Org",H3:H95) -> 132800
A102: People | G102: =SUMIF(C3:C95,"People",G3:G95) -> 88 | H102: =SUMIF(C3:C95,"People",H3:H95) -> 17600
A103: Physical | G103: =SUMIF(C3:C95,"Physical",G3:G95) -> 84 | H103: =SUMIF(C3:C95,"Physical",H3:H95) -> 16800
A104: Tech | G104: =SUMIF(C3:C95,"Tech",G3:G95) -> 848 | H104: =SUMIF(C3:C95,"Tech",H3:H95) -> 169600

Sheet severity_legend
A1: Severity legend (input options for column F)
A2: Value | B2: Meaning
A3: compliant | B3: Control is fully met. Evidence exists. No remediation required.
A4: partial | B4: Control is partially met. Some evidence exists; gaps in either coverage or documentation.
A5: gap | B5: Control is not met. Remediation required before certifiable posture.
A6: unknown | B6: Current state not yet known. Discovery item for next iteration.
A8: Current-state options (input column E):
A9: Value | B9: Meaning
A10: strong | B10: Native control in place; evidence-ready
A11: moderate | B11: Control in place but documentation gaps or partial coverage
A12: weak | B12: Practice exists but no formal control or evidence
A13: absent | B13: No practice; full implementation needed
A14: unknown | B14: Discovery required

Sheet assumptions
A1: Workload Estimator Assumptions
A2: Assumption | B2: Value | C2: Notes
A3: Loaded engineering rate ($/hr) | B3: 200 | C3: Should match cost-model loaded rate
A4: Effective FTE count for ISO remediation | B4: 3 | C4: How many FTEs working on Phase 2 in parallel
A5: Effective hours per FTE-week | B5: 30 | C5: 40 nominal − 25% overhead
A6: Compliance-pressure factor (for valuation discount) | B6: 0.7 | C6: See valuation-impact-formulas Formula 1
A7: Skill version | B7: saas-acquisition-diligence v1.0
A8: Linked cost-model run | B8: {path to cost-model-output.xlsx} | C8: Cross-reference

Sheet valuation_impact
A1: Valuation Impact — Gap-to-discount math
A2: Line | B2: Best ($) | C2: Expected ($) | D2: Worst ($)
A3: Total ISMS-gap remediation cost (linked from gap_inventory) | B3: =gap_inventory!H96*0.7 -> 235760 | C3: =gap_inventory!H96 -> 336800 | D3: =gap_inventory!H96*1.5 -> 505200
A4: Compliance-pressure factor | B4: 0.5 | C4: =assumptions!$B$6 -> 0.7 | D4: 1
A5: Discount-for-ISMS-gap (price reduction) | B5: =B3*B4 -> 117880 | C5: =C3*C4 -> 235760 | D5: =D3*D4 -> 505200
