Workbook

Sheet target
A1: Field | B1: Value | C1: Confidence | D1: Notes
A2: Target name | B2: RapidPOS LLC | C2: confirmed
A3: Type | B3: Counterpoint VAR | C3: confirmed
A4: Customer count | B4: 50 | C4: guess | D4: Founder verification needed
A5: Aggregate ARR ($) | B5: 2700000 | C5: guess | D5: Target-profile midpoint $3-6M; midpoint $4.5M flagged elsewhere
A6: Stores aggregate | B6: 1500 | C6: guess | D6: Range 500-2,500
A7: Team headcount | B7: 9 | C7: guess | D7: Range 6-12
A8: Senior engineers | B8: 3 | C8: guess | D8: Range 2-5; 1-2 are flight-risk-critical
A9: Verticals served | B9: garden / gun / wine / specialty food / feed-and-tack | C9: confirmed
A10: Open ticket count | B10: 115 | C10: guess | D10: Range 80-150
A11: Weekly inflow tickets | B11: 40 | C11: guess | D11: Range 30-50
A12: % repeat-cause | B12: 0.65 | C12: guess | D12: Range 60-70%; load-bearing for A1+A2 sizing
A13: Customer-bespoke % | B13: 0.3 | C13: guess | D13: Range 30%; 70% silently-repeating
A14: Modernization appetite | B14: moderate | C14: guess | D14: Conservative team; needs to be sold on cloud narrative
A15: Suitor landscape | B15: 1-2 PE rollup interest likely | C15: guess | D15: Implicit clock 6-12 months

Sheet customers
A1: Cohort | B1: Customer count | C1: % of total | D1: ARR per customer ($) | E1: Cohort ARR ($) | F1: Notes
A2: Eager (compliance-pressured / multi-store) | B2: 12 | C2: =B2/$B$5 | D2: 75000 | E2: =B2*D2 | F2: Migrate Phase B (M6-18)
A3: Steady (single/small-multi location) | B3: 28 | C3: =B3/$B$5 | D3: 45000 | E3: =B3*D3 | F3: Migrate Phase C (M18-36)
A4: Laggard (will not modernize) | B4: 10 | C4: =B4/$B$5 | D4: 35000 | E4: =B4*D4 | F4: Stay on Counterpoint; founder-team supports
A5: TOTAL | B5: =SUM(B2:B4) | C5: =SUM(C2:C4) | E5: =SUM(E2:E4)

Sheet ildwac_lift
A1: Cohort | B1: Customers | C1: Avg devices | D1: Conversion difficulty | E1: Hours per customer | F1: Total hours | G1: $ at $200/hr
A2: Eager | B2: =customers!B2 | C2: 8 | D2: 1.2 | E2: =C2*40*D2 | F2: =B2*E2 | G2: =F2*200
A3: Steady | B3: =customers!B3 | C3: 4 | D3: 1 | E3: =C3*40*D3 | F3: =B3*E3 | G3: =F3*200
A4: Laggard | B4: =customers!B4 | C4: 3 | D4: 0.8 | E4: =C4*40*D4 | F4: =B4*E4 | G4: =F4*200
A5: TOTAL | F5: =SUM(F2:F4) | G5: =SUM(G2:G4)
A8: Note: | B8: ILDWAC = Item × Location × Device × MCP × Port × Weighted-Average-Cost (patent #63/991,596). Conversion difficulty multiplier > 1 for serialized inventory; > 1.5 for multi-vendor port mix.

Sheet crdm_lift
A1: Cohort | B1: Customers | C1: Custom tables/customer | D1: Hours per table | E1: Hours per customer | F1: Total hours | G1: $ at $200/hr
A2: Eager | B2: =customers!B2 | C2: 12 | D2: 8 | E2: =C2*D2 | F2: =B2*E2 | G2: =F2*200
A3: Steady | B3: =customers!B3 | C3: 8 | D3: 8 | E3: =C3*D3 | F3: =B3*E3 | G3: =F3*200
A4: Laggard | B4: =customers!B4 | C4: 5 | D4: 8 | E4: =C4*D4 | F4: =B4*E4 | G4: =F4*200
A5: TOTAL | F5: =SUM(F2:F4) | G5: =SUM(G2:G4)
A8: Note: | B8: CRDM = Canary Retail Data Model, anchored on GSLM (Walmart Intl 2009). Mapping each customer's Counterpoint tables + VAR-proprietary extensions onto CRDM. Hours/table covers schema mapping, adapter dev, validation.

Sheet gcp_infra
A1: Workload | B1: T0 (today, $/mo) | C1: T1 (eager-cohort, $/mo) | D1: T2 (steady + new-logo, $/mo) | E1: T3 (Global-50 anchor, $/mo)
A2: 1. POS adapter ingress | B2: 0 | C2: 1500 | D2: 6000 | E2: 25000
A3: 2. TSP transaction streaming | B3: 0 | C3: 1200 | D3: 5000 | E3: 20000
A4: 3. CRDM canonical store (Cloud SQL → AlloyDB) | B4: 0 | C4: 3500 | D4: 12000 | E4: 60000
A5: 4. ILDWAC service | B5: 0 | C5: 1000 | D5: 4000 | E5: 18000
A6: 5. RIB batch + blockchain anchor | B6: 100 | C6: 600 | D6: 1800 | E6: 6000
A7: 6. Hawk case management | B7: 0 | C7: 900 | D7: 3000 | E7: 12000
A8: 7. Owl search + RAG | B8: 0 | C8: 1500 | D8: 5000 | E8: 22000
A9: 8. LLM inference (Vertex AI) | B9: 200 | C9: 20000 | D9: 60000 | E9: 250000
A10: 9. Edge agent (per-store) | B10: 0 | C10: 5000 | D10: 18000 | E10: 80000
A11: 10. Identity / auth | B11: 0 | C11: 700 | D11: 2200 | E11: 8000
A12: 11. Notifications (SendGrid + Twilio) | B12: 100 | C12: 1500 | D12: 5500 | E12: 22000
A13: 12. Reporting / BI (BigQuery + Looker) | B13: 0 | C13: 3000 | D13: 9000 | E13: 35000
... A19: 18. Agentic ops fabric (A1-A5) | B19: 0 | C19: 8000 | D19: 20000 | E19: 60000
A20: TOTAL monthly | B20: =SUM(B2:B19) | C20: =SUM(C2:C19) | D20: =SUM(D2:D19) | E20: =SUM(E2:E19)
A21: ANNUALIZED | B21: =B20*12 | C21: =C20*12 | D21: =D20*12 | E21: =E20*12

Sheet program_cost
A1: Component | B1: Best ($) | C1: Expected ($) | D1: Worst ($) | E1: Source
A2: ISO 27001 — 15 critical-mass controls remediation | B2: 80000 | C2: 104000 | D2: 140000 | E2: diligence/rapidpos/02; 520 hrs × $200, ±35%
A3: ISO 27001 — remaining 78 controls remediation | B3: 180000 | C3: 233000 | D3: 310000 | E3: diligence/rapidpos/02; ~1,164 hrs
A4: ISMS framework (policy + governance) | B4: 30000 | C4: 60000 | D4: 100000 | E4: 200-400 hrs
A5: Stage 1 + Stage 2 audit fees | B5: 20000 | C5: 35000 | D5: 50000 | E5: industry range
A6: Surveillance audit (Y2-3 ongoing) | B6: 20000 | C6: 30000 | D6: 40000 | E6: annual × 2 yrs
A7: ILDWAC conversion (across cohorts) | B7: =ildwac_lift!G5*0.7 | C7: =ildwac_lift!G5 | D7: =ildwac_lift!G5*1.4 | E7: ildwac_lift sheet
A8: CRDM mapping (across cohorts) | B8: =crdm_lift!G5*0.7 | C8: =crdm_lift!G5 | D8: =crdm_lift!G5*1.4 | E8: crdm_lift sheet
A9: GCP infra (T1 annualized × 18 months) | B9: =gcp_infra!C22*1.5 | C9: =gcp_infra!C22*1.5 | D9: =gcp_infra!C22*1.5 | E9: gcp_infra sheet T1 col
A10: Day-1 agentic ops compute (Phase A) | B10: 36000 | C10: 48000 | D10: 72000 | E10: $8k/mo × 6 mo
A11: Wyoming counsel (entity formation + ongoing) | B11: 25000 | C11: 45000 | D11: 80000 | E11: Phase 1 + Phase 2 hourly
A12: Compliance-architecture lead role (Y1) | B12: 80000 | C12: 120000 | D12: 180000 | E12: cash component for runway
A13: Engineering team retention pool (RapidPOS senior eng) | B13: 100000 | C13: 200000 | D13: 350000 | E13: retention-package estimate
A14: TOTAL Phase A+B (18mo program) | B14: =SUM(B2:B13) | C14: =SUM(C2:C13) | D14: =SUM(D2:D13)

Sheet glide_path
A1: Month | B1: Phase | C1: Milestone | D1: Cohort wave | E1: Compliance gate
A2: M1 | B2: A | C2: Acquisition close OR channel-partnership executed | D2: — | E2: Day-1 agentic ops deployed
A3: M3 | B3: A | C3: 8 of 15 critical-mass controls remediated; sandbox infra live | D3: — | E3: Internal review
A4: M6 | B4: A | C4: All 15 critical-mass controls remediated; sandbox DriftPOS live | D4: Eager cohort identified | E4: Pre-Stage-1 dry run
A5: M9 | B5: B | C5: ISO Stage 1 audit clean; first eager-cohort customer in sandbox | D5: Eager wave 1 begins | E5: Stage 1 sign-off
A6: M12 | B6: B | C6: DriftPOS GA; eager-cohort wave 1 in production | D6: Eager wave 1 in prod | E6: Stage 2 observation triggered
A7: M15 | B7: B | C7: Eager-cohort wave 2 underway; steady cohort begins | D7: Steady cohort begins | E7: Stage 2 observation in progress
A8: M18 | B8: B | C8: ISO 27001 certified; eager-cohort fully migrated | D8: Steady cohort migrating | E8: Certificate issued
A9: M24 | B9: C | C9: Steady cohort migration complete; new-logo wins | D9: New-logo wave begins | E9: SOC 2 Type II observation start

Sheet assumptions
A1: Assumption | B1: Value | C1: Used in | D1: Notes
A2: Engineering hourly rate | B2: 200 | C2: ildwac_lift, crdm_lift, program_cost | D2: Internal blended
A3: Compliance-pressure factor (gap-to-discount) | B3: 0.7 | C3: valuation contexts | D3: Range 0.5 (theoretical) - 1.0 (acute)
A4: Lineage-decay coefficient α (substrate) | B4: 0.5 | C4: substrate governance | D4: Per namespace; default 0.5
A5: Phase 1 founder-mint duration (months) | B5: 18 | C5: substrate phase mechanics | D5: Per bylaws
A6: Eager-cohort fraction of customer base | B6: =customers!C2 | C6: cost-model sizing | D6: Live link to customers tab
A7: Steady-cohort fraction | B7: =customers!C3 | C7: cost-model sizing | D7: Live link
A8: Laggard fraction | B8: =customers!C4 | C8: cost-model sizing | D8: Live link
A9: ISO 27001 critical-mass control count | B9: 15 | C9: DriftPOS-blocking gate | D9: Per saas-acquisition-diligence skill ref/07
A10: ISO 27001 total Annex A control count | B10: 93 | C10: full audit scope | D10: ISO 27001:2022 standard
A11: Hours per critical-mass ISO control (avg) | B11: 35 | C11: remediation sizing | D11: 520 / 15
A12: GCP T1 monthly aggregate ($) | B12: =gcp_infra!C22 | C12: annualized run-rate | D12: Live from gcp_infra
A13: Program duration Phase A+B (months) | B13: 18 | C13: program_cost summation
